kmp_utils
