Metadata-Version: 2.1
Name: kmp-utils
Version: 1.0.1
Summary: Implementation of KMP algorithm and simple generalizations.
Home-page: http://pypi.python.org/pypi/kmp_utils/
Author: Algorithms Path
Author-email: support@algorithmspath.com
License: MIT
Platform: UNKNOWN
Classifier: License :: OSI Approved :: MIT License
Classifier: Programming Language :: Python :: 3
Classifier: Programming Language :: Python :: 3.7
Requires-Python: >=3
